saterys/app.py
saterys/cli.py
saterys/core.py
saterys/scheduling.py
saterys/nodes/NDVI.py
saterys/nodes/NDWI.py
saterys/nodes/PCA.py
saterys/nodes/hello.py
saterys/nodes/input.py
saterys/nodes/script.py
saterys/nodes/sum.py
saterys/nodes/training_sample.py
saterys/static/index.html
saterys/static/assets/ContrastTheme-CpW2ne2a.js
saterys/static/assets/Controls-BfC7-EJX.js
saterys/static/assets/DrawerController-ZXfKNTdC.css
saterys/static/assets/DrawerController-yZeCUFhu.js
saterys/static/assets/Icon-CBehOuwm.js
saterys/static/assets/Minimap-qf37tA8b.js
saterys/static/assets/ThemeToggle-CdyaYN41.js
saterys/static/assets/index-BRw4aYKO.js
saterys/static/assets/index-BkhPcXpp.css
saterys/static/assets/vite-C4kziZTZ.svg
saterys-0.3.9.dist-info/licenses/LICENSE
saterys-0.3.9.dist-info/METADATA
saterys-0.3.9.dist-info/WHEEL
saterys-0.3.9.dist-info/entry_points.txt
saterys-0.3.9.dist-info/top_level.txt
saterys-0.3.9.dist-info/RECORD
