Metadata-Version: 2.4
Name: saterys
Version: 0.3.9
Summary: Saterys — Scalable Analysis Toolkit for Earth Remote sYStemS
Author-email: Sebastian Sanchez Bernal <bastian@example.com>
License: MIT
Project-URL: Homepage, https://saterys.com
Project-URL: Repository, https://github.com/bastian6666/saterys
Project-URL: Issues, https://github.com/bastian6666/saterys/issues
Classifier: Development Status :: 3 - Alpha
Classifier: Intended Audience :: Science/Research
Classifier: Topic :: Scientific/Engineering :: GIS
Classifier: License :: OSI Approved :: MIT License
Classifier: Programming Language :: Python :: 3
Classifier: Programming Language :: Python :: 3.9
Classifier: Programming Language :: Python :: 3.10
Classifier: Programming Language :: Python :: 3.11
Classifier: Programming Language :: Python :: 3.12
Requires-Python: >=3.9
License-File: LICENSE
Requires-Dist: fastapi>=0.110
Requires-Dist: uvicorn[standard]>=0.23
Requires-Dist: pydantic>=2
Requires-Dist: numpy>=1.26
Requires-Dist: rio-tiler>=6
Requires-Dist: rasterio>=1.3
Requires-Dist: fiona>=1.9
Requires-Dist: pyproj>=3.6
Requires-Dist: shapely>=2.0
Requires-Dist: APScheduler>=3.10.4
Requires-Dist: SQLAlchemy>=2.0
Requires-Dist: pytz>=2024.1
Requires-Dist: tzlocal>=5.2
Dynamic: license-file
